LICENSE.txt
README.md
setup.cfg
setup.py
hcgamelib/__init__.py
hcgamelib/const.py
hcgamelib/gamelib.py
hcgamelib.egg-info/PKG-INFO
hcgamelib.egg-info/SOURCES.txt
hcgamelib.egg-info/dependency_links.txt
hcgamelib.egg-info/requires.txt
hcgamelib.egg-info/top_level.txt