Metadata-Version: 2.1
Name: hcgamelib
Version: 0.2.994
Summary: Games!
Home-page: https://github.com/Doppelganger-phi
Download-URL: https://github.com/Doppelganger-phi/hcgamelib/archive/refs/tags/v0.2.994.tar.gz
Author: Doppelganger
Author-email: admin@doppelganger.eu.org
License: MIT
Keywords: games,hc
Classifier: Development Status :: 3 - Alpha
Classifier: Intended Audience :: Developers
Classifier: Topic :: Software Development :: Build Tools
Classifier: License :: OSI Approved :: MIT License
Classifier: Programming Language :: Python :: 3
Classifier: Programming Language :: Python :: 3.4
Classifier: Programming Language :: Python :: 3.5
Classifier: Programming Language :: Python :: 3.6
Classifier: Programming Language :: Python :: 3.7
Classifier: Programming Language :: Python :: 3.8
Classifier: Programming Language :: Python :: 3.9
Classifier: Programming Language :: Python :: 3.10
Classifier: Programming Language :: Python :: 3.11
Classifier: Programming Language :: Python :: 3.12
License-File: LICENSE.txt
